<?xml version="1.0" encoding="utf-8" ?><dwsync><file name="404.html" server="s179635.gridserver.com/domains/xinyiphilina.com/html/" local="3461675586" remote="318763443871253592" Dst="-1" /><file name="animation.html" server="s179635.gridserver.com/domains/xinyiphilina.com/html/" local="3469291535" remote="318763443871253592" Dst="-1" /><file name="bio.html" server="s179635.gridserver.com/domains/xinyiphilina.com/html/" local="3474770341" remote="318763443871253592" Dst="-1" /><file name="contact.html" server="s179635.gridserver.com/domains/xinyiphilina.com/html/" local="3474937668" remote="318763443871253592" Dst="-1" /><file name="index.html" server="s179635.gridserver.com/domains/xinyiphilina.com/html/" local="3469291300" remote="318763443871253652" Dst="-1" /><file name="photography.html" server="s179635.gridserver.com/domains/xinyiphilina.com/html/" local="3478367857" remote="318763443871253652" Dst="-1" /><file name="work.html" server="s179635.gridserver.com/domains/xinyiphilina.com/html/" local="3474763093" remote="318763443871253892" Dst="-1" /><file name="LICENSE.md" server="s179635.gridserver.com/domains/xinyiphilina.com/html/" local="3461675586" remote="318763443871253652" Dst="-1" /><file name=".DS_Store" server="s179635.gridserver.com/domains/xinyiphilina.com/html/" local="3478366665" remote="318763443871253592" Dst="-1" /><file name="link.txt" server="s179635.gridserver.com/domains/xinyiphilina.com/html/" local="3469298558" remote="318763443871253652" Dst="-1" /></dwsync>